dftpy/__init__.py
dftpy/__main__.py
dftpy/constants.py
dftpy/ewald.py
dftpy/fft.py
dftpy/field.py
dftpy/grid.py
dftpy/interface.py
dftpy/inverter.py
dftpy/ions.py
dftpy/linear_solver.py
dftpy/math_utils.py
dftpy/optimize.py
dftpy/time_data.py
dftpy/api/__init__.py
dftpy/api/api4ase.py
dftpy/api/dftd4.py
dftpy/config/__init__.py
dftpy/config/config.py
dftpy/config/config_entry.py
dftpy/config/configentries.json
dftpy/cui/__init__.py
dftpy/cui/main.py
dftpy/density/__init__.py
dftpy/density/density.py
dftpy/formats/__init__.py
dftpy/formats/ase_io.py
dftpy/formats/cube.py
dftpy/formats/den.py
dftpy/formats/io.py
dftpy/formats/npy.py
dftpy/formats/pmg_io.py
dftpy/formats/qepp.py
dftpy/formats/snpy.py
dftpy/formats/vasp.py
dftpy/formats/xsf.py
dftpy/formats/xyz.py
dftpy/functional/__init__.py
dftpy/functional/abstract_functional.py
dftpy/functional/external_potential.py
dftpy/functional/functional_output.py
dftpy/functional/hartree.py
dftpy/functional/semilocal_xc.py
dftpy/functional/total_functional.py
dftpy/functional/kedf/__init__.py
dftpy/functional/kedf/fp.py
dftpy/functional/kedf/gga.py
dftpy/functional/kedf/hc.py
dftpy/functional/kedf/kernel.py
dftpy/functional/kedf/lkt.py
dftpy/functional/kedf/lwt.py
dftpy/functional/kedf/mgp.py
dftpy/functional/kedf/sm.py
dftpy/functional/kedf/tf.py
dftpy/functional/kedf/vw.py
dftpy/functional/kedf/wt.py
dftpy/functional/nonadiabatic/__init__.py
dftpy/functional/nonadiabatic/jp.py
dftpy/functional/nonadiabatic/wcdhc.py
dftpy/functional/pseudo/__init__.py
dftpy/functional/pseudo/abstract_pseudo.py
dftpy/functional/pseudo/layer_pseudo.py
dftpy/functional/pseudo/psp.py
dftpy/functional/pseudo/recpot.py
dftpy/functional/pseudo/upf.py
dftpy/functional/pseudo/usp.py
dftpy/functional/pseudo/xml.py
dftpy/functional/xc/__init__.py
dftpy/functional/xc/rvv10.py
dftpy/functional/xc/semilocal_xc.py
dftpy/functional/xc/xc.json
dftpy/invert/__init__.py
dftpy/invert/analysis.py
dftpy/mixer/__init__.py
dftpy/mixer/linear.py
dftpy-2.0.0.dist-info/LICENSE.txt
dftpy-2.0.0.dist-info/METADATA
dftpy-2.0.0.dist-info/WHEEL
dftpy-2.0.0.dist-info/top_level.txt
dftpy-2.0.0.dist-info/RECORD
